pyDIMM/__init__.py
pyDIMM/_dirichlet_multinomial_mixture.py
pyDIMM-0.2.0.dist-info/LICENSE
pyDIMM-0.2.0.dist-info/METADATA
pyDIMM-0.2.0.dist-info/WHEEL
pyDIMM-0.2.0.dist-info/top_level.txt
pyDIMM-0.2.0.dist-info/RECORD
