Metadata-Version: 2.1
Name: pyDIMM
Version: 0.2.0
Summary: A Python Dirichlet-multinomial Mixture Model
Author-email: Ziqi Rong <ziqirong@umich.edu>
Project-URL: Homepage, https://github.com/Jck-R/pyDIMM
Project-URL: Bug Tracker, https://github.com/Jck-R/pyDIMM/issues
Classifier: Programming Language :: Python :: 3
Classifier: License :: OSI Approved :: BSD License
Classifier: Operating System :: OS Independent
Requires-Python: >=3.7
License-File: LICENSE
